LICENSE
MANIFEST.in
README.md
setup.py
aolesrtc/.DS_Store
aolesrtc/__init__.py
aolesrtc/aolesrtc.py
aolesrtc.egg-info/PKG-INFO
aolesrtc.egg-info/SOURCES.txt
aolesrtc.egg-info/dependency_links.txt
aolesrtc.egg-info/top_level.txt
aolesrtc/lib/darwin/arm64/_aolesrtc_python_api.so
aolesrtc/lib/linux/.DS_Store
aolesrtc/lib/linux/x86_64/.DS_Store
aolesrtc/lib/linux/x86_64/_aolesrtc_python_api.so
aolesrtc/lib/linux/x86_64/libaolesrtc.so
aolesrtc/lib/linux/x86_64/lib/libabsl_bad_any_cast_impl.so
aolesrtc/lib/linux/x86_64/lib/libabsl_bad_any_cast_impl.so.2301.0.0
aolesrtc/lib/linux/x86_64/lib/libabsl_bad_optional_access.so
aolesrtc/lib/linux/x86_64/lib/libabsl_bad_optional_access.so.2301.0.0
aolesrtc/lib/linux/x86_64/lib/libabsl_bad_variant_access.so
aolesrtc/lib/linux/x86_64/lib/libabsl_bad_variant_access.so.2301.0.0
aolesrtc/lib/linux/x86_64/lib/libabsl_base.so
aolesrtc/lib/linux/x86_64/lib/libabsl_base.so.2301.0.0
aolesrtc/lib/linux/x86_64/lib/libabsl_city.so
aolesrtc/lib/linux/x86_64/lib/libabsl_city.so.2301.0.0
aolesrtc/lib/linux/x86_64/lib/libabsl_civil_time.so
aolesrtc/lib/linux/x86_64/lib/libabsl_civil_time.so.2301.0.0
aolesrtc/lib/linux/x86_64/lib/libabsl_cord.so
aolesrtc/lib/linux/x86_64/lib/libabsl_cord.so.2301.0.0
aolesrtc/lib/linux/x86_64/lib/libabsl_cord_internal.so
aolesrtc/lib/linux/x86_64/lib/libabsl_cord_internal.so.2301.0.0
aolesrtc/lib/linux/x86_64/lib/libabsl_cordz_functions.so
aolesrtc/lib/linux/x86_64/lib/libabsl_cordz_functions.so.2301.0.0
aolesrtc/lib/linux/x86_64/lib/libabsl_cordz_handle.so
aolesrtc/lib/linux/x86_64/lib/libabsl_cordz_handle.so.2301.0.0
aolesrtc/lib/linux/x86_64/lib/libabsl_cordz_info.so
aolesrtc/lib/linux/x86_64/lib/libabsl_cordz_info.so.2301.0.0
aolesrtc/lib/linux/x86_64/lib/libabsl_cordz_sample_token.so
aolesrtc/lib/linux/x86_64/lib/libabsl_cordz_sample_token.so.2301.0.0
aolesrtc/lib/linux/x86_64/lib/libabsl_crc32c.so
aolesrtc/lib/linux/x86_64/lib/libabsl_crc32c.so.2301.0.0
aolesrtc/lib/linux/x86_64/lib/libabsl_crc_cord_state.so
aolesrtc/lib/linux/x86_64/lib/libabsl_crc_cord_state.so.2301.0.0
aolesrtc/lib/linux/x86_64/lib/libabsl_crc_cpu_detect.so
