Metadata-Version: 2.1
Name: aolesrtc
Version: 1.0.3
Summary: A easy & simple rtc library supporting janus & p2p
Home-page: 
Author: aoles
Author-email: young.aoles@qq.com
License: MIT License
Platform: macosx_arm64
Platform: linux_x86_64
Classifier: Development Status :: 3 - Alpha
Classifier: Intended Audience :: Developers
Classifier: License :: OSI Approved :: MIT License
Classifier: Programming Language :: Python :: 3.10
Classifier: Topic :: Software Development :: Libraries
Classifier: Operating System :: MacOS
Classifier: Operating System :: POSIX :: Linux
Requires-Python: ==3.10.13
License-File: LICENSE
